patronus_examples/__init__.py
patronus_examples/otel_tracing_integration.py
patronus_examples/task_openai.py
patronus_examples/tracing.py
patronus_examples/experiments/__init__.py
patronus_examples/experiments/evaluator_class.py
patronus_examples/experiments/evaluator_function.py
patronus_examples/experiments/evaluator_remote_pii.py
patronus_examples/experiments/patronus.yaml
patronus_examples/experiments/weighted_evaluators.py
patronus_examples/tracking/__init__.py
patronus_examples/tracking/anthropic_weather.py
patronus_examples/tracking/crewai_weather.py
patronus_examples/tracking/langchain_weather.py
patronus_examples/tracking/openai_agents_weather.py
patronus_examples/tracking/openai_weather.py
patronus_examples/tracking/otel_openai_weather.py
patronus_examples/tracking/pydanticai_weather.py
patronus_examples/tracking/smolagents_weather.py
patronus_examples-0.1.17.dist-info/METADATA
patronus_examples-0.1.17.dist-info/WHEEL
patronus_examples-0.1.17.dist-info/RECORD
